README.md
setup.py
ryze/__init__.py
ryze/classes.py
ryze/endpoints.py
ryze/scraper.py
ryze.egg-info/PKG-INFO
ryze.egg-info/SOURCES.txt
ryze.egg-info/dependency_links.txt
ryze.egg-info/requires.txt
ryze.egg-info/top_level.txt