Metadata-Version: 2.1
Name: ryze
Version: 0.0.1
Summary: League of Legends game updates wrapper and scrapper
Home-page: UNKNOWN
Author: André Sousa
Author-email: andrematosdesousa@gmail.com
License: MIT
Project-URL: Source, https://github.com/sousa-andre/ryze
Platform: UNKNOWN
